take_forecast/__init__.py
take_forecast/pipeline.py
take_forecast/project_context.py
take_forecast/run.py
take_forecast/evaluate/__init__.py
take_forecast/evaluate/nodes.py
take_forecast/fit/__init__.py
take_forecast/fit/nodes.py
take_forecast/posprocess/__init__.py
take_forecast/posprocess/nodes.py
take_forecast/predict/__init__.py
take_forecast/predict/nodes.py
take_forecast/preprocess/__init__.py
take_forecast/preprocess/nodes.py
take_forecast/project_template/.kedro.yml
take_forecast/project_template/conf/base/logging.yml
take_forecast/project_template/conf/base/parameters.yml
take_forecast/project_template/conf/base/catalog/base.yml
take_forecast/project_template/conf/base/pipelines/evaluate.yml
take_forecast/project_template/conf/base/pipelines/fit.yml
take_forecast/project_template/conf/base/pipelines/predict.yml
take_forecast/project_template/conf/base/pipelines/tune.yml
take_forecast/project_template/conf/local/.gitkeep
take_forecast/tune/__init__.py
take_forecast/tune/nodes.py
take_forecast/utils/__init__.py
take_forecast/utils/build_pipeline.py
take_forecast/utils/build_project_structure.py
tests/evaluate/__init__.py
tests/evaluate/test_nodes.py
tests/fit/__init__.py
tests/fit/test_nodes.py
tests/posprocess/__init__.py
tests/posprocess/test_nodes.py
tests/predict/__init__.py
tests/predict/test_nodes.py
tests/preprocess/__init__.py
tests/preprocess/test_nodes.py
tests/tune/__init__.py
tests/tune/test_nodes.py
tests/utils/__init__.py
tests/utils/test_build_pipeline.py
take_forecast-1.0.0.dist-info/METADATA
take_forecast-1.0.0.dist-info/WHEEL
take_forecast-1.0.0.dist-info/entry_points.txt
take_forecast-1.0.0.dist-info/top_level.txt
take_forecast-1.0.0.dist-info/RECORD
