Metadata-Version: 2.1
Name: take-forecast
Version: 1.0.0
Summary: This module performs time series forecasting using Kedro pipelines.
Home-page: UNKNOWN
Author: Squad XD
Author-email: analytics.dar@take.net
License: MIT License
Keywords: time series,forecast
Platform: UNKNOWN
Classifier: Programming Language :: Python :: 3
Classifier: Operating System :: OS Independent
Requires-Dist: kedro (==0.15.9)
Requires-Dist: kedro-viz (<4.0,>=3.2.0)
Requires-Dist: nbstripout (==0.3.3)
Requires-Dist: python-dateutil (==2.8.0)
Requires-Dist: pytest-cov (<3.0,>=2.8.1)
Requires-Dist: pytest-mock (<2.0,>=1.7.1)
Requires-Dist: pytest (<4.0,>=3.4)
Requires-Dist: six (==1.14.0)
Requires-Dist: twine
Requires-Dist: wheel (==0.32.2)
Requires-Dist: matplotlib (==3.1.3)
Requires-Dist: pandas (<=0.25.3)
Requires-Dist: seaborn
Requires-Dist: sklearn
Requires-Dist: statsmodels (>=0.11.1)
Requires-Dist: pyodbc
Provides-Extra: docs
Requires-Dist: sphinx (<2.0,>=1.6.3); extra == 'docs'
Requires-Dist: sphinx-rtd-theme (==0.4.1); extra == 'docs'
Requires-Dist: nbsphinx (==0.3.4); extra == 'docs'
Requires-Dist: nbstripout (==0.3.3); extra == 'docs'
Requires-Dist: recommonmark (==0.5.0); extra == 'docs'
Requires-Dist: sphinx-autodoc-typehints (==1.6.0); extra == 'docs'
Requires-Dist: sphinx-copybutton (==0.2.5); extra == 'docs'
Requires-Dist: jupyter-client (<6.0,>=5.1.0); extra == 'docs'
Requires-Dist: tornado (<6.0,>=4.2); extra == 'docs'
Requires-Dist: ipykernel (<5.0,>=4.8.1); extra == 'docs'
Provides-Extra: notebook
Requires-Dist: ipython (<8.0,>=7.13.0); extra == 'notebook'
Requires-Dist: jupyter (<2.0,>=1.0.0); extra == 'notebook'
Requires-Dist: jupyter-client (<6.0,>=5.1.0); extra == 'notebook'
Requires-Dist: jupyterlab (==0.31.1); extra == 'notebook'
